comwares/__init__.py
comwares/captcha/__init__.py
comwares/captcha/captcha_dev.py
comwares/captcha/icredit_captcha.py
comwares/captcha/slider.py
comwares/commons/__init__.py
comwares/commons/logger.py
comwares/commons/md5.py
comwares/commons/path_funcs.py
comwares/commons/sorting.py
comwares/commons/string_funcs.py
comwares/commons/time_funcs.py
comwares/crawler/__init__.py
comwares/crawler/user_agents.py
comwares/data/__init__.py
comwares/data/loaders.py
comwares/data/mongo_to_pg.py
comwares/data/pandas_utils.py
comwares/data/pg_utils.py
comwares/decorators/__init__.py
comwares/decorators/batchify.py
comwares/decorators/time.py
comwares/e-mail/__init__.py
comwares/e-mail/check.py
comwares/e-mail/exmail.py
comwares/e-mail/send.py
comwares/google/__init__.py
comwares/google/auth.py
comwares/google/gdrive.py
comwares/google/sheets.py
comwares/google/values.py
comwares/image/__init__.py
comwares/image/io.py
comwares/image/visualize.py
comwares/pdf/__init__.py
comwares/pdf/b64_transfer.py
comwares/pdf/pdf_analyzer.py
comwares/tencent/__init__.py
comwares/tencent/cos.py
comwares/tencent/sms.py
comwares/tencent/translate.py
comwares/traffic/__init__.py
comwares/traffic/alexacn.py
comwares/video/__init__.py
comwares/video/snap.py
comwares/webhooks/__init__.py
comwares/webhooks/chanify.py
comwares/webhooks/feishu.py
comwares/webhooks/work_weixin.py
comwares-0.1.5.dist-info/METADATA
comwares-0.1.5.dist-info/WHEEL
comwares-0.1.5.dist-info/top_level.txt
comwares-0.1.5.dist-info/RECORD
